thepipe/__init__.py
thepipe/core.py
thepipe/logger.py
thepipe/provenance.py
thepipe/tools.py
thepipe/tests/test_core.py
thepipe/tests/test_provenance.py
thepipe/tests/test_tools.py
thepipe-1.3.8.dist-info/LICENSE
thepipe-1.3.8.dist-info/METADATA
thepipe-1.3.8.dist-info/WHEEL
thepipe-1.3.8.dist-info/top_level.txt
thepipe-1.3.8.dist-info/RECORD
