Metadata-Version: 2.1
Name: thepipe
Version: 1.3.8
Summary: A lightweight, general purpose pipeline framework.
Home-page: http://github.com/tamasgal/thepipe
Author: Tamas Gal
Author-email: tgal@km3net.de
Platform: any
Classifier: Intended Audience :: Developers
Classifier: Intended Audience :: Science/Research
Classifier: Programming Language :: Python
Requires-Python: >=3.5
License-File: LICENSE
Requires-Dist: python-dateutil
Requires-Dist: numpy
Requires-Dist: pip (>=9)
Requires-Dist: psutil
Requires-Dist: pytz
Requires-Dist: setuptools-scm
Requires-Dist: toml
Provides-Extra: dev
Requires-Dist: mock ; extra == 'dev'
Requires-Dist: pytest (>=4.6) ; extra == 'dev'
Requires-Dist: pytest-cov ; extra == 'dev'
Requires-Dist: codecov ; extra == 'dev'
Requires-Dist: numpy ; extra == 'dev'
Requires-Dist: numpydoc ; extra == 'dev'
Requires-Dist: pillow ; extra == 'dev'
Requires-Dist: pydocstyle ; extra == 'dev'
Requires-Dist: sphinx-rtd-theme ; extra == 'dev'
Requires-Dist: sphinx ; extra == 'dev'
Requires-Dist: sphinx-autoapi ; extra == 'dev'
Requires-Dist: sphinxcontrib-napoleon ; extra == 'dev'
Requires-Dist: sphinxcontrib-programoutput ; extra == 'dev'
Requires-Dist: sphinxcontrib-websupport ; extra == 'dev'
